mgo_ai/__init__.py
mgo_ai/ai_interface/__init__.py
mgo_ai/ai_interface/ai_base.cpython-310-x86_64-linux-gnu.so
mgo_ai/ai_interface/cascade_trainer.cpython-310-x86_64-linux-gnu.so
mgo_ai/mgo_ml_base/__init__.py
mgo_ai/mgo_ml_base/compile.py
mgo_ai/mgo_ml_base/format_map.cpython-310-x86_64-linux-gnu.so
mgo_ai/mgo_ml_base/format_map.py
mgo_ai/mgo_ml_base/formatter.cpython-310-x86_64-linux-gnu.so
mgo_ai/mgo_ml_base/formatter.py
mgo_ai/mgo_ml_base/local_models.cpython-310-x86_64-linux-gnu.so
mgo_ai/mgo_ml_base/local_models.py
mgo_ai/mgo_ml_base/mgo_trainer.cpython-310-x86_64-linux-gnu.so
mgo_ai/mgo_ml_base/mgo_trainer.py
mgoaiwrkpi-0.5.4.dist-info/METADATA
mgoaiwrkpi-0.5.4.dist-info/WHEEL
mgoaiwrkpi-0.5.4.dist-info/top_level.txt
mgoaiwrkpi-0.5.4.dist-info/RECORD
