Metadata-Version: 2.4
Name: mgoaiwrkpi
Version: 0.5.4
Author: Kelly Kapowski
Requires-Python: >=3.10
Requires-Dist: psycopg2
Requires-Dist: pandas==1.5.3
Requires-Dist: numpy<=1.26.0
Requires-Dist: SQLAlchemy==1.*
Requires-Dist: Cython
Requires-Dist: cryptography<=42.0.8
Requires-Dist: requests
Requires-Dist: sshtunnel
Requires-Dist: keyrings.google.artifactregistry-auth
Requires-Dist: h2o==3.46.0.7
